llguidance-1.3.0.dist-info/METADATA
llguidance-1.3.0.dist-info/WHEEL
llguidance-1.3.0.dist-info/licenses/LICENSE
llguidance/__init__.py
llguidance/_grammar_from.py
llguidance/_lib.pyd
llguidance/_lib.pyi
llguidance/_struct_tag.py
llguidance/_tokenizer.py
llguidance/_util.py
llguidance/cli.py
llguidance/gbnf_to_lark.py
llguidance/hf.py
llguidance/llamacpp.py
llguidance/mlx.py
llguidance/numpy.py
llguidance/py.typed
llguidance/tiktoken.py
llguidance/torch.py
llguidance-1.3.0.dist-info/RECORD
