Metadata-Version: 2.4
Name: llguidance
Version: 1.3.0
License-File: LICENSE
Summary: Bindings for the Low-level Guidance (llguidance) Rust library for use within Guidance
Author: Michal Moskal
License-Expression: MIT
Requires-Python: >=3.9
Project-URL: repository, https://github.com/microsoft/llguidance
Project-URL: issue_tracker, https://github.com/microsoft/llguidance/issues
